thrift_sasl/__init__.py
thrift_sasl-0.4.3a2.dist-info/LICENSE
thrift_sasl-0.4.3a2.dist-info/METADATA
thrift_sasl-0.4.3a2.dist-info/WHEEL
thrift_sasl-0.4.3a2.dist-info/top_level.txt
thrift_sasl-0.4.3a2.dist-info/RECORD
